xcalibu/Xcalibuds.py
xcalibu/__init__.py
xcalibu/demo_xcalibu.py
xcalibu/device_test.py
xcalibu/test_xcalibu.py
xcalibu/xcalibu.py
xcalibu/examples/U32a_1_table.txt
xcalibu/examples/U32a_table_non_monotonic.txt
xcalibu/examples/book5.txt
xcalibu/examples/cubic.calib
xcalibu/examples/cubic_poly.calib
xcalibu/examples/gauss.calib
xcalibu/examples/hpz_ring_Ry.calib
xcalibu/examples/hpz_ring_Tz.calib
xcalibu/examples/poly.calib
xcalibu/examples/qepro.calib
xcalibu/examples/table.calib
xcalibu/examples/table_1_column.txt
xcalibu/examples/table_2_col.calib
xcalibu/examples/table_2_columns.txt
xcalibu/examples/u32a_poly.calib
xcalibu/examples/undu_table.calib
xcalibu/examples/unsorted_table.calib
xcalibu-1.0.1.dist-info/LICENSE
xcalibu-1.0.1.dist-info/METADATA
xcalibu-1.0.1.dist-info/WHEEL
xcalibu-1.0.1.dist-info/entry_points.txt
xcalibu-1.0.1.dist-info/top_level.txt
xcalibu-1.0.1.dist-info/RECORD
