Metadata-Version: 2.1
Name: xcalibu
Version: 1.0.1
Summary: Calibration library
Maintainer: Cyril Guilloud (ESRF-BCU)
License: GNU LESSER GENERAL PUBLIC LICENSE
Classifier: License :: OSI Approved :: GNU Lesser General Public License v3 (LGPLv3)
Classifier: Operating System :: OS Independent
Classifier: Programming Language :: Python
Requires-Python: >=3.7
License-File: LICENSE
